pyscivis/.bokeh
pyscivis/__init__.py
pyscivis/__main__.py
pyscivis/app_hooks.py
pyscivis/arguments.py
pyscivis/bokeh.ext.json
pyscivis/config.toml
pyscivis/flask_deploy.py
pyscivis/index.ts
pyscivis/main.py
pyscivis/package.json
pyscivis/tsconfig.json
pyscivis/__pycache__/__init__.cpython-310.pyc
pyscivis/__pycache__/__main__.cpython-310.pyc
pyscivis/__pycache__/arguments.cpython-310.pyc
pyscivis/dist/pyscivis.js
pyscivis/dist/pyscivis.js.map
pyscivis/dist/pyscivis.json
pyscivis/dist/pyscivis.min.js
pyscivis/dist/compiled/index.d.ts
pyscivis/dist/compiled/index.d.ts.map
pyscivis/dist/compiled/index.js
pyscivis/dist/compiled/index.js.map
pyscivis/dist/compiled/visualizer/models/filetree.d.ts
pyscivis/dist/compiled/visualizer/models/filetree.d.ts.map
pyscivis/dist/compiled/visualizer/models/filetree.js
pyscivis/dist/compiled/visualizer/models/filetree.js.map
pyscivis/dist/compiled/visualizer/models/index.d.ts
pyscivis/dist/compiled/visualizer/models/index.d.ts.map
pyscivis/dist/compiled/visualizer/models/index.js
pyscivis/dist/compiled/visualizer/models/index.js.map
pyscivis/dist/compiled/visualizer/models/offset_log_color_mapper.d.ts
pyscivis/dist/compiled/visualizer/models/offset_log_color_mapper.d.ts.map
pyscivis/dist/compiled/visualizer/models/offset_log_color_mapper.js
pyscivis/dist/compiled/visualizer/models/offset_log_color_mapper.js.map
pyscivis/dist/compiled/visualizer/models/offset_log_tick_formatter.d.ts
pyscivis/dist/compiled/visualizer/models/offset_log_tick_formatter.d.ts.map
pyscivis/dist/compiled/visualizer/models/offset_log_tick_formatter.js
pyscivis/dist/compiled/visualizer/models/offset_log_tick_formatter.js.map
pyscivis/dist/compiled/visualizer/models/throttled_slider.d.ts
pyscivis/dist/compiled/visualizer/models/throttled_slider.d.ts.map
pyscivis/dist/compiled/visualizer/models/throttled_slider.js
pyscivis/dist/compiled/visualizer/models/throttled_slider.js.map
pyscivis/static/css/bootstrap-3.4.0.min.css
pyscivis/static/css/custom.css
pyscivis-0.9.2.dist-info/LICENSE
pyscivis-0.9.2.dist-info/METADATA
pyscivis-0.9.2.dist-info/WHEEL
pyscivis-0.9.2.dist-info/entry_points.txt
pyscivis-0.9.2.dist-info/top_level.txt
pyscivis-0.9.2.dist-info/RECORD
