Metadata-Version: 2.1
Name: pyscivis
Version: 0.9.2
Summary: A visualization tool for ISMRMRD files. Can be used standalone or embedded into Jupyter Notebooks.
Home-page: https://gitlab.com/chi-imrt/pyscivis/pyscivis
Author: Jannik Meinecke
Project-URL: Bug Tracker, https://gitlab.com/chi-imrt/pyscivis/pyscivis/issues
Classifier: Programming Language :: Python :: 3
Classifier: License :: OSI Approved :: GNU General Public License v3 or later (GPLv3+)
Classifier: Operating System :: OS Independent
Requires-Python: >=3.8
License-File: LICENSE
Requires-Dist: bokeh (==2.4.3)
Requires-Dist: tornado (>=6.2)
Requires-Dist: ismrmrd (>=1.12.0)
Requires-Dist: Pillow (>=8.4.0)
Requires-Dist: numpy (>=1.22.3)
Requires-Dist: numba (>=0.55.2)
Requires-Dist: attr (>=0.3.2)
Requires-Dist: desert (>=2020.11.18)
Requires-Dist: toml (>=0.10.2)
Requires-Dist: pptree (>=3.1)
Requires-Dist: defusedxml (>=0.7.1)
Provides-Extra: testing
Requires-Dist: pytest (>=6.2.4) ; extra == 'testing'
Requires-Dist: pytest-cov ; extra == 'testing'
Requires-Dist: pytest-dependency ; extra == 'testing'
